template/__init__.py
template/config.py
template/constants.py
template/context.py
template/directive.py
template/document.py
template/filters.py
template/grammar.py
template/iterator.py
template/parser.py
template/plugins.py
template/provider.py
template/service.py
template/stash.py
template/test.py
template/util.py
template/view.py
template/vmethods.py
template/namespace/__init__.py
template/namespace/constants.py
template/plugin/__init__.py
template/plugin/datafile.py
template/plugin/date.py
template/plugin/directory.py
template/plugin/file.py
template/plugin/filter.py
template/plugin/format.py
template/plugin/html.py
template/plugin/image.py
template/plugin/iterator.py
template/plugin/math_plugin.py
template/plugin/string.py
template/plugin/table.py
template/plugin/url.py
template/plugin/view.py
template/plugin/wrap.py
Template_Toolkit_Python_2-0.2.dist-info/LICENSE
Template_Toolkit_Python_2-0.2.dist-info/METADATA
Template_Toolkit_Python_2-0.2.dist-info/WHEEL
Template_Toolkit_Python_2-0.2.dist-info/top_level.txt
Template_Toolkit_Python_2-0.2.dist-info/RECORD
