Metadata-Version: 2.1
Name: Template-Toolkit-Python-2
Version: 0.2
Summary: Python port of the Template Toolkit
Home-page: http://template-toolkit.org/python/
Author: Sean McAfee
Author-email: eefacm@gmail.com
License-File: LICENSE
